{
  "project_info": {
    "project_number": "677071312267",
    "project_id": "oakley-saves",
    "storage_bucket": "oakley-saves.appspot.com"
  },
  "client": [
    {
      "client_info": {
        "mobilesdk_app_id": "1:677071312267:android:e4e7fa5cd13c6e3ff60b8e",
        "android_client_info": {
          "package_name": "com.economiaon"
        }
      },
      "oauth_client": [
        {
          "client_id": "677071312267-d5bbamkt4vaeikvkbuq5453lhn0dgh4s.apps.googleusercontent.com",
          "client_type": 3
        }
      ],
      "api_key": [
        {
          "current_key": "AIzaSyBcVLgxdvGdu8HV4rwNXDhXLwKgfOuQOxU"
        }
      ],
      "services": {
        "appinvite_service": {
          "other_platform_oauth_client": [
            {
              "client_id": "677071312267-d5bbamkt4vaeikvkbuq5453lhn0dgh4s.apps.googleusercontent.com",
              "client_type": 3
            }
          ]
        }
      }
    }
  ],
  "configuration_version": "1"
}